[
  {
    "children": [
      {
        "text": "Important Links",
        "bold": true
      }
    ],
    "type": "h2"
  },
  {
    "children": [
      {
        "text": ""
      },
      {
        "type": "a",
        "url": "https://discord.com/invite/sknhvXw",
        "children": [
          {
            "text": ""
          }
        ]
      },
      {
        "text": ""
      },
      {
        "type": "a",
        "url": "https://discord.com/invite/sknhvXw",
        "children": [
          {
            "text": "Discord Server"
          }
        ]
      },
      {
        "text": ""
      }
    ],
    "type": "paragraph"
  },
  {
    "children": [
      {
        "text": "History",
        "bold": true
      }
    ],
    "type": "h2"
  },
  {
    "children": [
      {
        "text": "Evolve was created by BiggestEntree 2019/6/12 as a casual singleplayer world "
      }
    ]
  },
  {
    "children": [
      {
        "text": "and later became a dedicated technical server on 2020/5/7 after Entree"
      }
    ]
  },
  {
    "children": [
      {
        "text": "redeemed 'Server Tour' on Xcum's twitch stream. At the time of said stream the world only had"
      }
    ]
  },
  {
    "children": [
      {
        "text": "the most basic of farms and shitty builds, the world also only had a single perimeter in the spawn chunks."
      }
    ]
  },
  {
    "children": [
      {
        "text": ""
      }
    ],
    "type": "h2"
  },
  {
    "children": [
      {
        "text": "Projects",
        "bold": true
      }
    ],
    "type": "h2"
  },
  {
    "children": [
      {
        "text": ""
      },
      {
        "type": "a",
        "url": "https://discord.com/invite/sknhvXw",
        "children": [
          {
            "text": ""
          }
        ]
      },
      {
        "text": ""
      }
    ]
  },
  {
    "children": [
      {
        "text": "Server Details",
        "bold": true
      }
    ],
    "type": "h2"
  },
  {
    "children": [
      {
        "text": ""
      },
      {
        "type": "a",
        "url": "discord.gg/sknhvXw",
        "children": [
          {
            "text": ""
          }
        ]
      },
      {
        "text": "Seed: -344398759534268713",
        "bold": true
      }
    ]
  },
  {
    "children": [
      {
        "text": ""
      }
    ]
  },
  {
    "children": [
      {
        "text": "   Additional Server Add-Ons:",
        "bold": true
      }
    ]
  },
  {
    "type": "ul",
    "children": [
      {
        "children": [
          {
            "text": "\tCareful Break"
          }
        ],
        "type": "li"
      },
      {
        "children": [
          {
            "text": "\tDragon Egg Bedrock Breaking"
          }
        ],
        "type": "li"
      },
      {
        "children": [
          {
            "text": "\tMissing Tools"
          }
        ],
        "type": "li"
      },
      {
        "children": [
          {
            "text": "\tShulkersSpawningInEndCities"
          }
        ],
        "type": "li"
      },
      {
        "children": [
          {
            "text": "\tNoXPCooldown"
          }
        ],
        "type": "li"
      },
      {
        "children": [
          {
            "text": "\tAdvanced Armor Stands"
          }
        ],
        "type": "li"
      },
      {
        "children": [
          {
            "text": "\tCraftable Elytra"
          }
        ],
        "type": "li"
      },
      {
        "children": [
          {
            "text": "        Lithium"
          }
        ],
        "type": "li"
      },
      {
        "children": [
          {
            "text": "        Phosphor"
          }
        ],
        "type": "li"
      },
      {
        "children": [
          {
            "text": "\tVacuum/Restock Shulkers"
          }
        ],
        "type": "li"
      },
      {
        "children": [
          {
            "text": "\tNon OP Scoreboard changes"
          }
        ],
        "type": "li"
      },
      {
        "children": [
          {
            "text": "\tCS Script"
          }
        ],
        "type": "li"
      }
    ]
  },
  {
    "children": [
      {
        "text": ""
      }
    ]
  },
  {
    "children": [
      {
        "text": ""
      }
    ]
  },
  {
    "children": [
      {
        "text": "Current Member List:",
        "bold": true
      },
      {
        "text": "            (As of 2021/1/11)"
      }
    ],
    "type": "h2"
  },
  {
    "children": [
      {
        "text": "   Admins:",
        "bold": true
      }
    ]
  },
  {
    "type": "ul",
    "children": [
      {
        "children": [
          {
            "text": "\tBiggestEntree89"
          }
        ],
        "type": "li"
      },
      {
        "children": [
          {
            "text": "\tFrey"
          }
        ],
        "type": "li"
      },
      {
        "children": [
          {
            "text": "\tTubaGuy98"
          }
        ],
        "type": "li"
      }
    ]
  },
  {
    "children": [
      {
        "text": "   Members:",
        "bold": true
      }
    ]
  },
  {
    "type": "ul",
    "children": [
      {
        "children": [
          {
            "text": "\tDJ_Hale"
          }
        ],
        "type": "li"
      },
      {
        "children": [
          {
            "text": "\tFeluk6174"
          }
        ],
        "type": "li"
      },
      {
        "children": [
          {
            "text": "\tjvt"
          }
        ],
        "type": "li"
      },
      {
        "children": [
          {
            "text": "\tMeowManian"
          }
        ],
        "type": "li"
      },
      {
        "children": [
          {
            "text": "\tmoop"
          }
        ],
        "type": "li"
      },
      {
        "children": [
          {
            "text": "\tNeopolis01"
          }
        ],
        "type": "li"
      },
      {
        "children": [
          {
            "text": "\tOceaneus"
          }
        ],
        "type": "li"
      },
      {
        "children": [
          {
            "text": "\tSkullTheSecond"
          }
        ],
        "type": "li"
      },
      {
        "children": [
          {
            "text": "\ttoggy"
          }
        ],
        "type": "li"
      },
      {
        "children": [
          {
            "text": "\tSouthernPixel"
          }
        ],
        "type": "li"
      }
    ]
  },
  {
    "children": [
      {
        "text": ""
      }
    ],
    "type": "paragraph"
  },
  {
    "children": [
      {
        "text": "   Semi-Member:",
        "bold": true
      }
    ],
    "type": "paragraph"
  },
  {
    "type": "ul",
    "children": [
      {
        "children": [
          {
            "text": "\tSpeedCuber"
          }
        ],
        "type": "li"
      },
      {
        "children": [
          {
            "text": "\tKrozjin"
          }
        ],
        "type": "li"
      }
    ]
  }
]